reladiff/__init__.py
reladiff/__main__.py
reladiff/config.py
reladiff/databases/__init__.py
reladiff/databases/_connect.py
reladiff/databases/base.py
reladiff/databases/bigquery.py
reladiff/databases/clickhouse.py
reladiff/databases/databricks.py
reladiff/databases/duckdb.py
reladiff/databases/mysql.py
reladiff/databases/oracle.py
reladiff/databases/postgresql.py
reladiff/databases/presto.py
reladiff/databases/redshift.py
reladiff/databases/snowflake.py
reladiff/databases/trino.py
reladiff/databases/vertica.py
reladiff/diff_tables.py
reladiff/hashdiff_tables.py
reladiff/info_tree.py
reladiff/joindiff_tables.py
reladiff/parse_time.py
reladiff/query_utils.py
reladiff/table_segment.py
reladiff/thread_utils.py
reladiff/utils.py
reladiff-0.6.0.dist-info/LICENSE
reladiff-0.6.0.dist-info/METADATA
reladiff-0.6.0.dist-info/WHEEL
reladiff-0.6.0.dist-info/entry_points.txt
reladiff-0.6.0.dist-info/RECORD
