Metadata-Version: 2.1
Name: reladiff
Version: 0.6.0
Summary: Command-line tool and Python library to efficiently diff rows across two different databases.
Home-page: https://github.com/erezsh/reladiff
License: MIT
Author: Erez Shinan
Author-email: erezshin@gmail.com
Requires-Python: >=3.8,<4.0
Classifier: Development Status :: 4 - Beta
Classifier: Environment :: Console
Classifier: Intended Audience :: Developers
Classifier: Intended Audience :: Information Technology
Classifier: Intended Audience :: System Administrators
Classifier: License :: OSI Approved :: MIT License
Classifier: Programming Language :: Python :: 3
Classifier: Programming Language :: Python :: 3.8
Classifier: Programming Language :: Python :: 3.9
Classifier: Programming Language :: Python :: 3.10
Classifier: Programming Language :: Python :: 3.11
Classifier: Programming Language :: Python :: 3.12
Classifier: Topic :: Database :: Database Engines/Servers
Classifier: Typing :: Typed
Provides-Extra: all
Provides-Extra: clickhouse
Provides-Extra: duckdb
Provides-Extra: mysql
Provides-Extra: oracle
Provides-Extra: postgresql
Provides-Extra: preql
Provides-Extra: presto
Provides-Extra: snowflake
Provides-Extra: trino
Provides-Extra: vertica
Requires-Dist: click (>=8.1)
Requires-Dist: clickhouse-driver ; extra == "clickhouse" or extra == "all"
Requires-Dist: cryptography ; extra == "snowflake" or extra == "all"
Requires-Dist: dsnparse
Requires-Dist: duckdb (>=0.6.0) ; extra == "duckdb" or extra == "all"
Requires-Dist: mysql-connector-python (>=8.0.29) ; extra == "mysql" or extra == "all"
Requires-Dist: presto-python-client ; extra == "presto" or extra == "all"
Requires-Dist: psycopg2-binary ; extra == "postgresql" or extra == "all"
Requires-Dist: rich
Requires-Dist: runtype (>=0.5.0)
Requires-Dist: snowflake-connector-python (>=2.7.2) ; extra == "snowflake" or extra == "all"
Requires-Dist: sqeleton (>=0.1.7,<0.2.0)
Requires-Dist: toml (>=0.10.2)
Requires-Dist: trino (>=0.314.0) ; extra == "trino" or extra == "all"
Project-URL: Documentation, https://reladiff.readthedocs.io/en/latest/
Project-URL: Repository, https://github.com/erezsh/reladiff
